ein/emptypackage/__init__.py
ein-1.0.1.dist-info/METADATA
ein-1.0.1.dist-info/WHEEL
ein-1.0.1.dist-info/top_level.txt
ein-1.0.1.dist-info/RECORD
