Metadata-Version: 2.1
Name: ein
Version: 1.0.1
Summary: namespace package for ein.plus
Home-page: UNKNOWN
Author: Qiangning Hong
Author-email: hongqn@ein.plus
License: MIT
Platform: UNKNOWN
Requires-Python: >=3.3
Provides-Extra: dev
Requires-Dist: twine ; extra == 'dev'
